honeybee_doe2/__init__.py
honeybee_doe2/__main__.py
honeybee_doe2/_extend_honeybee.py
honeybee_doe2/config.py
honeybee_doe2/construction.py
honeybee_doe2/grouping.py
honeybee_doe2/load.py
honeybee_doe2/programtype.py
honeybee_doe2/reader.py
honeybee_doe2/schedule.py
honeybee_doe2/simulation.py
honeybee_doe2/util.py
honeybee_doe2/writer.py
honeybee_doe2/cli/__init__.py
honeybee_doe2/cli/translate.py
honeybee_doe2/properties/__init__.py
honeybee_doe2/properties/model.py
honeybee_doe2/properties/room.py
honeybee_doe2-0.23.3.dist-info/licenses/LICENSE
honeybee_doe2-0.23.3.dist-info/METADATA
honeybee_doe2-0.23.3.dist-info/WHEEL
honeybee_doe2-0.23.3.dist-info/entry_points.txt
honeybee_doe2-0.23.3.dist-info/top_level.txt
honeybee_doe2-0.23.3.dist-info/RECORD
